adafruit_sdcard.py
adafruit_circuitpython_sd-3.3.27.dist-info/licenses/LICENSE
adafruit_circuitpython_sd-3.3.27.dist-info/METADATA
adafruit_circuitpython_sd-3.3.27.dist-info/WHEEL
adafruit_circuitpython_sd-3.3.27.dist-info/top_level.txt
adafruit_circuitpython_sd-3.3.27.dist-info/RECORD
